ddfr/__init__.py
ddfr/ddfr.py
ddfr-0.9.2.dist-info/LICENSE
ddfr-0.9.2.dist-info/METADATA
ddfr-0.9.2.dist-info/WHEEL
ddfr-0.9.2.dist-info/entry_points.txt
ddfr-0.9.2.dist-info/top_level.txt
ddfr-0.9.2.dist-info/RECORD
