Metadata-Version: 2.1
Name: ddfr
Version: 0.9.2
Summary: A lightweight Python utility to detect dns records that are suspected as dangling.
Home-page: https://github.com/PlaytikaSecurity/ddfr
Author: Playtika Ltd.
Author-email: security@playtika.com
Classifier: Programming Language :: Python :: 3
Classifier: License :: OSI Approved :: Apache Software License
Classifier: Operating System :: OS Independent
Requires-Python: >=3.7
License-File: LICENSE
Requires-Dist: requests==2.32.3
Requires-Dist: pyOpenSSL==22.0.0
Requires-Dist: certifi==2024.8.30
